botwinick_utils/__init__.py
botwinick_utils/compat.py
botwinick_utils/io.py
botwinick_utils/net.py
botwinick_utils/paths.py
botwinick_utils/pretty.py
botwinick_utils/regex.py
botwinick_utils/util.py
botwinick_utils/binary/__init__.py
botwinick_utils/binary/b32.py
botwinick_utils/binary/l32.py
botwinick_utils/logs/__init__.py
botwinick_utils/platforms/__init__.py
botwinick_utils/platforms/bg_threads.py
botwinick_utils/platforms/linux.py
botwinick_utils/platforms/python.py
botwinick_utils/platforms/threading.py
botwinick_utils/platforms/windows.py
botwinick_utils/platforms/tk/__init__.py
botwinick_utils/platforms/tk/logging_handler.py
botwinick_utils/platforms/tk/widgets/__init__.py
botwinick_utils/platforms/tk/widgets/checkbox_frame.py
botwinick_utils/platforms/tk/widgets/reorderable_listbox.py
botwinick_utils/progress_reporting/__init__.py
botwinick_utils/progress_reporting/tracker.py
botwinick_utils-0.0.20.dist-info/LICENSE
botwinick_utils-0.0.20.dist-info/METADATA
botwinick_utils-0.0.20.dist-info/WHEEL
botwinick_utils-0.0.20.dist-info/top_level.txt
botwinick_utils-0.0.20.dist-info/RECORD
