Metadata-Version: 2.1
Name: botwinick-utils
Version: 0.0.20
Summary: Assorted Utilities and platform code
Home-page: https://github.com/dbotwinick/botwinick_utils
Author: Drew Botwinick
Author-email: foss@drewbotwinick.com
License: UNKNOWN
Platform: UNKNOWN
Classifier: Development Status :: 4 - Beta
Classifier: Intended Audience :: Developers
Classifier: Programming Language :: Python :: 3
Classifier: License :: OSI Approved :: BSD License
Classifier: Operating System :: OS Independent
Requires-Python: >=3.9
License-File: LICENSE
